LICENSE.txt
MANIFEST.in
README.rst
setup.cfg
setup.py
pertinosdk/__init__.py
pertinosdk.egg-info/PKG-INFO
pertinosdk.egg-info/SOURCES.txt
pertinosdk.egg-info/dependency_links.txt
pertinosdk.egg-info/requires.txt
pertinosdk.egg-info/top_level.txt