Metadata-Version: 1.1
Name: pertinosdk
Version: 0.1.0
Summary: Python package for communicating with Pertino.
Home-page: https://github.com/Pertino/pertino-sdk-python
Author: Pertino Inc.
Author-email: developer@pertino.com
License: LICENSE.txt
Download-URL: https://github.com/Pertino/pertino-sdk-python/tarball/0.1
Keywords: pertino,sdk,api
Platform: any
Classifier: Development Status :: 3 - Alpha
Classifier: Natural Language :: English
Classifier: Operating System :: Unix
Classifier: Programming Language :: Python
Classifier: Programming Language :: Unix Shell
Classifier: Topic :: Software Development :: Libraries :: Python Modules
